{"format":1,"version":"4.4.2","settings":"1ed7ee4faff8a31af7cdb8f8d9be68f3","files":{"src_lodegML___init___py":{"hash":"4911cff48f6b9e153df4c1a3ecaded19","index":{"nums":[1,0,0,0,0,0,0],"html_filename":"src_lodegML___init___py.html","relative_filename":"src/lodegML/__init__.py"}},"src_lodegML_auto_plot_py":{"hash":"296d93cfe61291933d4ebb7621b200a6","index":{"nums":[1,175,0,110,0,0,0],"html_filename":"src_lodegML_auto_plot_py.html","relative_filename":"src/lodegML/auto_plot.py"}},"src_lodegML_cache_py":{"hash":"04a9efa5ab257d8536d0ad273c8b6d3a","index":{"nums":[1,46,0,46,0,0,0],"html_filename":"src_lodegML_cache_py.html","relative_filename":"src/lodegML/cache.py"}},"src_lodegML_connection_to_mongo_py":{"hash":"626891912fe47e52cebe6e02f4bfd281","index":{"nums":[1,12,0,0,0,0,0],"html_filename":"src_lodegML_connection_to_mongo_py.html","relative_filename":"src/lodegML/connection_to_mongo.py"}},"src_lodegML_data_extraction_py":{"hash":"14fcc859ef1a34d560198e265b84cc9f","index":{"nums":[1,349,0,25,0,0,0],"html_filename":"src_lodegML_data_extraction_py.html","relative_filename":"src/lodegML/data_extraction.py"}},"src_lodegML_ml_py":{"hash":"0537ed3637c18a9ee42eb1e1409861f3","index":{"nums":[1,78,0,6,0,0,0],"html_filename":"src_lodegML_ml_py.html","relative_filename":"src/lodegML/ml.py"}},"src_lodegML_system_py":{"hash":"f99451a44f6cd0bacd12edb8bb4bbaf7","index":{"nums":[1,249,0,127,0,0,0],"html_filename":"src_lodegML_system_py.html","relative_filename":"src/lodegML/system.py"}},"src_lodegML_utility_queries_py":{"hash":"9cc912b0182bdf2556a2b0d905048c88","index":{"nums":[1,64,0,4,0,0,0],"html_filename":"src_lodegML_utility_queries_py.html","relative_filename":"src/lodegML/utility_queries.py"}},"src_lodegML_import_export_py":{"hash":"59da3a40a4c5b53390b4a338cc237118","index":{"nums":[1,96,0,45,0,0,0],"html_filename":"src_lodegML_import_export_py.html","relative_filename":"src/lodegML/import_export.py"}},"src_lodegML_configure___init___py":{"hash":"182b2dca469bf063cbcf996d517b03da","index":{"nums":[1,0,0,0,0,0,0],"html_filename":"src_lodegML_configure___init___py.html","relative_filename":"src/lodegML/configure/__init__.py"}},"src_lodegML_configure_configurations_py":{"hash":"7d2d4cdd9e7956c3e3b6a3ca27558740","index":{"nums":[1,8,0,2,0,0,0],"html_filename":"src_lodegML_configure_configurations_py.html","relative_filename":"src/lodegML/configure/configurations.py"}},"src_lodegML_configure_configure_py":{"hash":"74bb6949e00f4f3bf70fe363f9598a2d","index":{"nums":[1,22,0,8,0,0,0],"html_filename":"src_lodegML_configure_configure_py.html","relative_filename":"src/lodegML/configure/configure.py"}},"src_lodegML_exceptions_py":{"hash":"09829aacc8f7bab64a37f50dbadaecbe","index":{"nums":[1,12,0,0,0,0,0],"html_filename":"src_lodegML_exceptions_py.html","relative_filename":"src/lodegML/exceptions.py"}},"src_lodegML_mongo_queries_py":{"hash":"d77522d304d3e5a65f701a65345eac20","index":{"nums":[1,52,0,0,0,0,0],"html_filename":"src_lodegML_mongo_queries_py.html","relative_filename":"src/lodegML/mongo_queries.py"}}}}